swarm_orchestrator/__init__.py
swarm_orchestrator/cli.py
swarm_orchestrator/config.py
swarm_orchestrator/decomposer.py
swarm_orchestrator/exploration.py
swarm_orchestrator/installation.py
swarm_orchestrator/mcp_client.py
swarm_orchestrator/orchestrator.py
swarm_orchestrator/schaltwerk.py
swarm_orchestrator/tui.py
swarm_orchestrator/voting.py
swarm_orchestrator/backends/__init__.py
swarm_orchestrator/backends/base.py
swarm_orchestrator/backends/cursor.py
swarm_orchestrator/backends/cursor_auth.py
swarm_orchestrator/backends/git_native.py
swarm_orchestrator/backends/git_native_store.py
swarm_orchestrator/backends/llm.py
swarm_orchestrator/backends/schaltwerk.py
swarm_orchestrator/swarm_mcp/__init__.py
swarm_orchestrator/swarm_mcp/compression.py
swarm_orchestrator/swarm_mcp/diff_utils.py
swarm_orchestrator/swarm_mcp/server.py
swarm_orchestrator/swarm_mcp/state.py
swarm_orchestrator/swarm_mcp/tools.py
swarm_orchestrator-0.2.0.dist-info/METADATA
swarm_orchestrator-0.2.0.dist-info/WHEEL
swarm_orchestrator-0.2.0.dist-info/entry_points.txt
swarm_orchestrator-0.2.0.dist-info/licenses/LICENSE
swarm_orchestrator-0.2.0.dist-info/RECORD
