Metadata-Version: 2.4
Name: swarm-orchestrator
Version: 0.2.0
Summary: Multi-agent consensus system using Schaltwerk + Claude Code
Project-URL: Homepage, https://github.com/rayen-faleh/swarm-orchestrator
Project-URL: Documentation, https://github.com/rayen-faleh/swarm-orchestrator#readme
Project-URL: Repository, https://github.com/rayen-faleh/swarm-orchestrator
Project-URL: Issues, https://github.com/rayen-faleh/swarm-orchestrator/issues
Project-URL: Changelog, https://github.com/rayen-faleh/swarm-orchestrator/blob/main/CHANGELOG.md
Author: Swarm Orchestrator Contributors
Maintainer: Swarm Orchestrator Contributors
License: MIT
License-File: LICENSE
Keywords: agents,ai,claude,consensus,llm,multi-agent,orchestrator,schaltwerk
Classifier: Development Status :: 3 - Alpha
Classifier: Environment :: Console
Classifier: Intended Audience :: Developers
Classifier: License :: OSI Approved :: MIT License
Classifier: Operating System :: OS Independent
Classifier: Programming Language :: Python :: 3
Classifier: Programming Language :: Python :: 3.11
Classifier: Programming Language :: Python :: 3.12
Classifier: Programming Language :: Python :: 3.13
Classifier: Topic :: Scientific/Engineering :: Artificial Intelligence
Classifier: Topic :: Software Development :: Libraries :: Python Modules
Classifier: Typing :: Typed
Requires-Python: >=3.11
Requires-Dist: anthropic>=0.40.0
Requires-Dist: click>=8.1.0
Requires-Dist: rich>=13.0.0
Provides-Extra: dev
Requires-Dist: pytest-asyncio>=0.24.0; extra == 'dev'
Requires-Dist: pytest>=8.0.0; extra == 'dev'
Requires-Dist: ruff>=0.6.0; extra == 'dev'
